essencia_model/__init__.py
essencia_model/base/__init__.py
essencia_model/base/enums.py
essencia_model/base/model.py
essencia_model/config.py
essencia_model/context.py
essencia_model/database.py
essencia_model-0.1.0.dist-info/WHEEL
essencia_model-0.1.0.dist-info/METADATA
essencia_model-0.1.0.dist-info/RECORD
