Metadata-Version: 2.1
Name: essencia-model
Version: 0.1.0
Summary: 
Author: Daniel Arantes
Requires-Python: >=3.9,<4.0
Classifier: Programming Language :: Python :: 3
Classifier: Programming Language :: Python :: 3.10
Classifier: Programming Language :: Python :: 3.9
Requires-Dist: Jinja2 (>=3.1.2,<4.0.0)
Requires-Dist: deta[async] (==1.1.0a2)
Requires-Dist: pydantic[dotenv,email] (>=1.10.4,<2.0.0)
Requires-Dist: starlette (>=0.24.0,<0.25.0)
